{
  "wallpapers": [
    {
      "startdate": "20260216",
      "fullstartdate": "202602160700",
      "enddate": "20260217",
      "url": "https://global.bing.com/th?id=OHR.PresidentsDay_EN-US6598155144_UHD.jpg&rf=LaDigue_UHD.jpg&pid=hp&w=3840&h=2160&rs=1&c=4",
      "urlbase": "/th?id=OHR.PresidentsDay_EN-US6598155144",
      "copyright": "Lincoln Memorial, Washington, DC (© Westend61/Getty Images)",
      "copyrightonly": "© Westend61/Getty Images",
      "title": "PresidentsDay",
      "desc": "Lincoln Memorial, Washington, DC (© Westend61/Getty Images)",
      "date": "2026-02-16",
      "bsTitle": "PresidentsDay",
      "download_url": "https://global.bing.com/th?id=OHR.PresidentsDay_EN-US6598155144_UHD.jpg",
      "thumbnail": "https://global.bing.com/th?id=OHR.PresidentsDay_EN-US6598155144_UHD.jpg&rf=LaDigue_UHD.jpg&pid=hp&w=384&h=216&rs=1&c=4",
      "featured_thumbnail": "https://global.bing.com/th?id=OHR.PresidentsDay_EN-US6598155144_UHD.jpg&rf=LaDigue_UHD.jpg&w=1000"
    }
  ],
  "updated_at": "2026-03-01T10:00:00.000000",
  "count": 1
}

